jr_exception_tools/__init__.py
jr_exception_tools/module_exceptions.py
jr_exception_tools-0.2.1.dist-info/LICENSE
jr_exception_tools-0.2.1.dist-info/METADATA
jr_exception_tools-0.2.1.dist-info/WHEEL
jr_exception_tools-0.2.1.dist-info/top_level.txt
jr_exception_tools-0.2.1.dist-info/RECORD
