Metadata-Version: 2.2
Name: jr_exception_tools
Version: 0.2.1
Summary: A abstract base class for exceptions
License: MIT
Project-URL: Repository, https://github.com/JuniorVieira99/jr_exceptions_tools
Classifier: Development Status :: 4 - Beta
Classifier: Intended Audience :: Developers
Classifier: License :: OSI Approved :: MIT License
Classifier: Programming Language :: Python :: 3
Classifier: Programming Language :: Python :: 3.12
Classifier: Topic :: Software Development :: Libraries :: Python Modules
Requires-Python: >=3.12.8
License-File: LICENSE
Requires-Dist: pytest>=8.3.4
Requires-Dist: rich>=13.9.4
